MianxiangduixiangDeJiaobenyuyanRuby/README.md
MianxiangduixiangDeJiaobenyuyanRuby/__init__.py
MianxiangduixiangDeJiaobenyuyanRuby/__main__.py
MianxiangduixiangDeJiaobenyuyanRuby/file.epub
MianxiangduixiangDeJiaobenyuyanRuby/index.html
MianxiangduixiangDeJiaobenyuyanRuby/css/__init__.py
MianxiangduixiangDeJiaobenyuyanRuby/css/annotations.css
MianxiangduixiangDeJiaobenyuyanRuby/css/main.css
MianxiangduixiangDeJiaobenyuyanRuby/css/normalize.css
MianxiangduixiangDeJiaobenyuyanRuby/css/popup.css
MianxiangduixiangDeJiaobenyuyanRuby/font/__init__.py
MianxiangduixiangDeJiaobenyuyanRuby/font/fontello.eot
MianxiangduixiangDeJiaobenyuyanRuby/font/fontello.svg
MianxiangduixiangDeJiaobenyuyanRuby/font/fontello.ttf
MianxiangduixiangDeJiaobenyuyanRuby/font/fontello.woff
MianxiangduixiangDeJiaobenyuyanRuby/img/__init__.py
MianxiangduixiangDeJiaobenyuyanRuby/img/annotator-glyph-sprite.png
MianxiangduixiangDeJiaobenyuyanRuby/img/annotator-icon-sprite.png
MianxiangduixiangDeJiaobenyuyanRuby/img/apple-touch-icon.png
MianxiangduixiangDeJiaobenyuyanRuby/img/cancelfullscreen.png
MianxiangduixiangDeJiaobenyuyanRuby/img/close.png
MianxiangduixiangDeJiaobenyuyanRuby/img/fullscreen.png
MianxiangduixiangDeJiaobenyuyanRuby/img/loader.gif
MianxiangduixiangDeJiaobenyuyanRuby/img/menu-icon.png
MianxiangduixiangDeJiaobenyuyanRuby/img/save.png
MianxiangduixiangDeJiaobenyuyanRuby/img/saved.png
MianxiangduixiangDeJiaobenyuyanRuby/img/settings-s.png
MianxiangduixiangDeJiaobenyuyanRuby/img/settings.png
MianxiangduixiangDeJiaobenyuyanRuby/img/star.png
MianxiangduixiangDeJiaobenyuyanRuby/js/__init__.py
MianxiangduixiangDeJiaobenyuyanRuby/js/epub.js
MianxiangduixiangDeJiaobenyuyanRuby/js/epub.min.js
MianxiangduixiangDeJiaobenyuyanRuby/js/epub.min.map
MianxiangduixiangDeJiaobenyuyanRuby/js/hooks.min.js
MianxiangduixiangDeJiaobenyuyanRuby/js/hooks.min.map
MianxiangduixiangDeJiaobenyuyanRuby/js/reader.js
MianxiangduixiangDeJiaobenyuyanRuby/js/reader.js.map
MianxiangduixiangDeJiaobenyuyanRuby/js/reader.min.js
mianxiangduixiang_de_jiaobenyuyan_ruby-2024.3.2.0.dist-info/METADATA
mianxiangduixiang_de_jiaobenyuyan_ruby-2024.3.2.0.dist-info/WHEEL
mianxiangduixiang_de_jiaobenyuyan_ruby-2024.3.2.0.dist-info/entry_points.txt
mianxiangduixiang_de_jiaobenyuyan_ruby-2024.3.2.0.dist-info/top_level.txt
mianxiangduixiang_de_jiaobenyuyan_ruby-2024.3.2.0.dist-info/RECORD
